edc_fieldsets/__init__.py
edc_fieldsets/apps.py
edc_fieldsets/fieldlist.py
edc_fieldsets/fieldset.py
edc_fieldsets/fieldsets.py
edc_fieldsets/fieldsets_modeladmin_mixin.py
edc_fieldsets/models.py
edc_fieldsets/urls.py
edc_fieldsets/tests/__init__.py
edc_fieldsets/tests/admin.py
edc_fieldsets/tests/forms.py
edc_fieldsets/tests/models.py
edc_fieldsets/tests/test_settings.py
edc_fieldsets/tests/visit_schedule.py
edc_fieldsets/tests/etc/user-aes-local.key
edc_fieldsets/tests/etc/user-aes-restricted.key
edc_fieldsets/tests/etc/user-rsa-local-private.pem
edc_fieldsets/tests/etc/user-rsa-local-public.pem
edc_fieldsets/tests/etc/user-rsa-restricted-private.pem
edc_fieldsets/tests/etc/user-rsa-restricted-public.pem
edc_fieldsets/tests/etc/user-salt-local.key
edc_fieldsets/tests/etc/user-salt-restricted.key
edc_fieldsets/tests/tests/__init__.py
edc_fieldsets/tests/tests/test_fieldset_admin.py
edc_fieldsets/tests/tests/test_fieldsets.py
edc_fieldsets-1.0.1.dist-info/AUTHORS
edc_fieldsets-1.0.1.dist-info/LICENSE
edc_fieldsets-1.0.1.dist-info/METADATA
edc_fieldsets-1.0.1.dist-info/WHEEL
edc_fieldsets-1.0.1.dist-info/top_level.txt
edc_fieldsets-1.0.1.dist-info/RECORD
